seqslab/__init__.py
seqslab/hive.py
seqslab/sqlalchemy/__init__.py
seqslab/sqlalchemy/hive.py
seqslab/superset/__init__.py
seqslab/superset/seqslab.py
seqslab_connector-0.9.6.data/data/requirements/requirements.txt
seqslab_connector-0.9.6.dist-info/LICENSE
seqslab_connector-0.9.6.dist-info/METADATA
seqslab_connector-0.9.6.dist-info/WHEEL
seqslab_connector-0.9.6.dist-info/entry_points.txt
seqslab_connector-0.9.6.dist-info/top_level.txt
seqslab_connector-0.9.6.dist-info/RECORD
