Metadata-Version: 2.1
Name: seqslab-connector
Version: 0.9.6
Summary: Atgenomix SeqsLab Connector for Python
Home-page: https://github.com/atgenomix/seqslab-connector
Author: Allen Chang
Author-email: allen.chang@atgenomix.com
License: Apache License, Version 2.0
Project-URL: Documentation, https://docs.atgenomix.com/
Project-URL: Repository, https://github.com/atgenomix/seqslab-connector
Platform: UNKNOWN
Classifier: Intended Audience :: Developers
Classifier: License :: OSI Approved :: Apache Software License
Classifier: Operating System :: OS Independent
Classifier: Topic :: Database :: Front-Ends
Classifier: Programming Language :: Python :: 3
Classifier: Programming Language :: Python :: 3.7
Classifier: Programming Language :: Python :: 3.8
Classifier: Programming Language :: Python :: 3.9
Classifier: Programming Language :: Python :: 3.10
Requires-Dist: pip >=22.0.4
Requires-Dist: PyHive >=0.6.5
Requires-Dist: thrift >=0.16.0
Requires-Dist: setuptools >=59.0.1
Provides-Extra: sqlalchemy
Requires-Dist: sqlalchemy >=1.3.0 ; extra == 'sqlalchemy'
Provides-Extra: superset
Requires-Dist: superset >=2.0.1 ; extra == 'superset'
